small_to_big_rag/__init__.py
small_to_big_rag/core.py
small_to_big_rag-0.1.0.dist-info/licenses/LICENSE
small_to_big_rag-0.1.0.dist-info/METADATA
small_to_big_rag-0.1.0.dist-info/WHEEL
small_to_big_rag-0.1.0.dist-info/top_level.txt
small_to_big_rag-0.1.0.dist-info/RECORD
