Metadata-Version: 2.4
Name: small-to-big-rag
Version: 0.1.0
Summary: Small-to-Big RAG implementation for more effective retrieval augmented generation
Home-page: https://github.com/WSIB-Innovation/small-to-big-package
Author: Your Name
Author-email: your.email@example.com
Classifier: Programming Language :: Python :: 3
Classifier: License :: OSI Approved :: MIT License
Classifier: Operating System :: OS Independent
Requires-Python: >=3.8
License-File: LICENSE
Requires-Dist: langchain-text-splitters>=0.0.1
Requires-Dist: openai>=1.0.0
Requires-Dist: chromadb>=0.4.0
Requires-Dist: python-dotenv>=1.0.0
Dynamic: author
Dynamic: author-email
Dynamic: classifier
Dynamic: description
Dynamic: description-content-type
Dynamic: home-page
Dynamic: license-file
Dynamic: requires-dist
Dynamic: requires-python
Dynamic: summary
